django_ethereum_events/__init__.py
django_ethereum_events/admin.py
django_ethereum_events/apps.py
django_ethereum_events/chainevents.py
django_ethereum_events/decoder.py
django_ethereum_events/event_listener.py
django_ethereum_events/exceptions.py
django_ethereum_events/forms.py
django_ethereum_events/models.py
django_ethereum_events/signals.py
django_ethereum_events/tasks.py
django_ethereum_events/utils.py
django_ethereum_events/web3_service.py
django_ethereum_events/management/__init__.py
django_ethereum_events/management/commands/__init__.py
django_ethereum_events/management/commands/reset_block_daemon.py
django_ethereum_events/migrations/0001_initial.py
django_ethereum_events/migrations/0002_auto_20180531_0806.py
django_ethereum_events/migrations/0003_auto_20180531_0836.py
django_ethereum_events/migrations/0004_failedeventlog.py
django_ethereum_events/migrations/0005_auto_20180713_1130.py
django_ethereum_events/migrations/__init__.py
django_ethereum_events/settings/__init__.py
django_ethereum_events/settings/dev.py
django_ethereum_events/settings/test.py
django_ethereum_events/tests/__init__.py
django_ethereum_events/tests/test_decoder.py
django_ethereum_events/tests/test_event_listener.py
django_ethereum_events/tests/contracts/__init__.py
django_ethereum_events/tests/contracts/bank.py
django_ethereum_events/tests/contracts/claim.py
example/management/__init__.py
example/management/commands/__init__.py
example/management/commands/clean_state.py
example/management/commands/register_events.py
example/management/commands/run_listener.py
example/management/commands/send_echo.py
example/migrations/__init__.py
django_ethereum_events-4.2.0.dist-info/LICENSE
django_ethereum_events-4.2.0.dist-info/METADATA
django_ethereum_events-4.2.0.dist-info/WHEEL
django_ethereum_events-4.2.0.dist-info/top_level.txt
django_ethereum_events-4.2.0.dist-info/RECORD
