Metadata-Version: 2.1
Name: django-ethereum-events
Version: 4.2.0
Summary: Django Ethereum Events
Home-page: https://github.com/artemistomaras/django-ethereum-events
Author: Artemios Tomaras
Author-email: artemistomaras@gmail.com
License: MIT License
Keywords: django ethereum
Platform: UNKNOWN
Classifier: Environment :: Web Environment
Classifier: Framework :: Django
Classifier: Framework :: Django :: 1.11
Classifier: Framework :: Django :: 2.0
Classifier: Framework :: Django :: 2.1
Classifier: Framework :: Django :: 2.2
Classifier: Framework :: Django :: 3.0
Classifier: Framework :: Django :: 3.1
Classifier: Intended Audience :: Developers
Classifier: License :: OSI Approved :: MIT License
Classifier: Operating System :: OS Independent
Classifier: Programming Language :: Python
Classifier: Programming Language :: Python :: 3.6
Classifier: Programming Language :: Python :: 3.7
Classifier: Topic :: Internet :: WWW/HTTP
Classifier: Topic :: Internet :: WWW/HTTP :: Dynamic Content
Requires-Python: >=3.6,<4
Requires-Dist: Django (>=1.11)
Requires-Dist: celery (>=3.1.25)
Requires-Dist: django-solo (>=1.1.0)
Requires-Dist: web3 (<6,>=5.5.0)
Provides-Extra: dev
Requires-Dist: eth-tester[py-evm] (==v0.2.0-beta.2) ; extra == 'dev'
Requires-Dist: tox (<2wheel,>=1.8.0twine>=1.13) ; extra == 'dev'
Requires-Dist: flake8 (==3.7.9) ; extra == 'dev'
Provides-Extra: linter
Requires-Dist: flake8 (==3.7.9) ; extra == 'linter'
Provides-Extra: tester
Requires-Dist: eth-tester[py-evm] (==v0.2.0-beta.2) ; extra == 'tester'
